robust/__init__.py
robust/angular.py
robust/bounds.py
robust/cocircular.py
robust/hints.py
robust/linear.py
robust/parallelogram.py
robust/projection.py
robust/utils.py
robust-0.2.7.dist-info/LICENSE
robust-0.2.7.dist-info/METADATA
robust-0.2.7.dist-info/WHEEL
robust-0.2.7.dist-info/top_level.txt
robust-0.2.7.dist-info/RECORD
