Metadata-Version: 2.1
Name: robust
Version: 0.2.7
Summary: Robust computational geometry predicates.
Home-page: https://github.com/lycantropos/robust/
Author: Azat Ibrakov
Author-email: azatibrakov@gmail.com
License: MIT License
Download-URL: https://github.com/lycantropos/robust/archive/master.zip
Platform: UNKNOWN
Classifier: License :: OSI Approved :: MIT License
Classifier: Programming Language :: Python :: 3.5
Classifier: Programming Language :: Python :: 3.6
Classifier: Programming Language :: Python :: 3.7
Classifier: Programming Language :: Python :: 3.8
Classifier: Programming Language :: Python :: 3.9
Classifier: Programming Language :: Python :: Implementation :: CPython
Classifier: Programming Language :: Python :: Implementation :: PyPy
Requires-Python: >=3.5
